fiases/__init__.py
fiases/address.py
fiases/address_del.py
fiases/address_upd.py
fiases/fias_data.py
fiases/fias_delta_update.py
fiases/fias_download.py
fiases/fias_info.py
fiases/fias_update.py
fiases/house_upd.py
fiases/houses.py
fiases/index_address.py
fiases/init_db.py
fiases/snapshot.py
fiases/update_info.py
fiases-1.8.103.dist-info/LICENSE
fiases-1.8.103.dist-info/METADATA
fiases-1.8.103.dist-info/WHEEL
fiases-1.8.103.dist-info/top_level.txt
fiases-1.8.103.dist-info/RECORD
