Metadata-Version: 2.1
Name: fiases
Version: 1.8.103
Summary: FIAS Elasticsearch integration
Home-page: https://github.com/u4097/elasticsearch-fias
Author: Oleg Sitnikov
Author-email: oleg.sitnikov@icloud.com
License: UNKNOWN
Platform: UNKNOWN
Classifier: Programming Language :: Python :: 3
Classifier: License :: OSI Approved :: MIT License
Classifier: Operating System :: OS Independent
Classifier: Development Status :: 4 - Beta
Classifier: Environment :: Web Environment
Classifier: Intended Audience :: Developers
Classifier: Topic :: Database
Classifier: Topic :: Software Development
Classifier: Natural Language :: Russian
Requires-Python: >=3.6
Requires-Dist: elasticsearch (>=7.1.0)
Requires-Dist: elasticsearch-dsl (>=7.1.0)
Requires-Dist: hurry.filesize (>=0.9)
Requires-Dist: rarfile (>=3.1)
Requires-Dist: tqdm (>=4.40.1)
Requires-Dist: urllib3 (>=1.25.7)
Requires-Dist: lxml (>=4.4.2)
Requires-Dist: py-dateutil (>=2.2)
Requires-Dist: requests (>=2.22.0)
